django_filebrowser_no_grappelli_staff-3.6.2.1.dist-info/RECORD
django_filebrowser_no_grappelli_staff-3.6.2.1.dist-info/metadata.json
django_filebrowser_no_grappelli_staff-3.6.2.1.dist-info/top_level.txt
django_filebrowser_no_grappelli_staff-3.6.2.1.dist-info/WHEEL
django_filebrowser_no_grappelli_staff-3.6.2.1.dist-info/METADATA
django_filebrowser_no_grappelli_staff-3.6.2.1.dist-info/DESCRIPTION.rst
django_filebrowser_no_grappelli_staff-3.6.2.1.dist-info/zip-safe
filebrowser/admin.py
filebrowser/decorators.py
filebrowser/sites.py
filebrowser/base.py
filebrowser/__init__.py
filebrowser/utils.py
filebrowser/widgets.py
filebrowser/models.py
filebrowser/fields.py
filebrowser/actions.py
filebrowser/storage.py
filebrowser/settings.py
filebrowser/forms.py
filebrowser/compat.py
filebrowser/signals.py
filebrowser/templates/filebrowser/custom_field.html
filebrowser/templates/filebrowser/upload.html
filebrowser/templates/filebrowser/delete_confirm.html
filebrowser/templates/filebrowser/detail.html
filebrowser/templates/filebrowser/createdir.html
filebrowser/templates/filebrowser/index.html
filebrowser/templates/filebrowser/version.html
filebrowser/templates/filebrowser/custom_upload_field.html
filebrowser/templates/filebrowser/include/breadcrumbs.html
filebrowser/templates/filebrowser/include/filelisting.html
filebrowser/templates/filebrowser/include/tableheader.html
filebrowser/templates/filebrowser/include/filter.html
filebrowser/templates/filebrowser/include/toolbar.html
filebrowser/templates/filebrowser/include/_response.html
filebrowser/templates/filebrowser/include/paginator.html
filebrowser/templates/filebrowser/widgets/fileinput.html
filebrowser/templates/filebrowser/widgets/clearablefileinput.html
filebrowser/locale/fr/LC_MESSAGES/django.mo
filebrowser/locale/fr/LC_MESSAGES/django.po
filebrowser/locale/ja/LC_MESSAGES/django.mo
filebrowser/locale/ja/LC_MESSAGES/django.po
filebrowser/locale/ja_JP/LC_MESSAGES/django.mo
filebrowser/locale/ja_JP/LC_MESSAGES/django.po
filebrowser/locale/vi/LC_MESSAGES/django.mo
filebrowser/locale/vi/LC_MESSAGES/django.po
filebrowser/locale/es/LC_MESSAGES/django.mo
filebrowser/locale/es/LC_MESSAGES/django.po
filebrowser/locale/sv/LC_MESSAGES/django.mo
filebrowser/locale/sv/LC_MESSAGES/django.po
filebrowser/locale/cs/LC_MESSAGES/django.mo
filebrowser/locale/cs/LC_MESSAGES/django.po
filebrowser/locale/pl_PL/LC_MESSAGES/django.mo
